{
  "version": "p23.m5",
  "readiness_id": "opl-shared-foundation-index-readiness-example-001",
  "shared_surface_id": "opl_shared_foundation_ownership",
  "governing_surface_ids": [
    "opl_shared_foundation",
    "opl_shared_foundation_ownership"
  ],
  "candidate_indexes": [
    {
      "index_id": "shared_asset_index",
      "current_state": "roadmap_only_future_only_reference_only_non_admitting",
      "indexed_families": [
        "data_assets",
        "references",
        "templates",
        "delivery_assets"
      ],
      "allowed_object_classes": [
        "data_assets",
        "references",
        "templates",
        "delivery_assets"
      ],
      "identifier_kinds": [
        "top_level_identifier",
        "reference_shape",
        "cross_domain_relation_hint"
      ],
      "current_public_surface_forbidden": true,
      "governing_refs": [
        {
          "ref_kind": "repo_path",
          "ref": "docs/shared-foundation.md",
          "label": "Shared Foundation"
        },
        {
          "ref_kind": "repo_path",
          "ref": "docs/shared-foundation-ownership.md",
          "label": "Shared Foundation Ownership"
        }
      ]
    },
    {
      "index_id": "shared_memory_index",
      "current_state": "roadmap_only_future_only_reference_only_non_admitting",
      "indexed_families": [
        "topic_memory",
        "review_memory",
        "venue_memory"
      ],
      "allowed_object_classes": [
        "topic_memory",
        "review_memory",
        "venue_memory"
      ],
      "identifier_kinds": [
        "top_level_identifier",
        "reference_shape",
        "cross_domain_relation_hint"
      ],
      "current_public_surface_forbidden": true,
      "governing_refs": [
        {
          "ref_kind": "repo_path",
          "ref": "docs/shared-foundation.md",
          "label": "Shared Foundation"
        },
        {
          "ref_kind": "repo_path",
          "ref": "docs/shared-foundation-ownership.md",
          "label": "Shared Foundation Ownership"
        }
      ]
    }
  ],
  "owner_split": [
    {
      "family_id": "data_assets",
      "index_ids": [
        "shared_asset_index"
      ],
      "opl_controls": [
        "top-level identity",
        "category",
        "reference shape",
        "cross-domain reuse rules"
      ],
      "domain_controls": [
        "canonical datasets",
        "derived study assets",
        "mutation history",
        "audit truth"
      ],
      "human_private_controls": [
        "raw exports",
        "staging files",
        "pre-admission materials"
      ],
      "must_not_move_into_opl_by_default": [
        "canonical runtime data truth"
      ],
      "governing_refs": [
        {
          "ref_kind": "repo_path",
          "ref": "docs/shared-foundation-ownership.md"
        }
      ]
    },
    {
      "family_id": "references",
      "index_ids": [
        "shared_asset_index"
      ],
      "opl_controls": [
        "shared reference categories",
        "reusable top-level reference index",
        "cross-domain citation semantics"
      ],
      "domain_controls": [
        "study-local usage",
        "domain-local annotation",
        "evidence packaging context"
      ],
      "human_private_controls": [
        "private reading lists",
        "notes",
        "preliminary collections"
      ],
      "must_not_move_into_opl_by_default": [
        "domain-specific evidence truth"
      ],
      "governing_refs": [
        {
          "ref_kind": "repo_path",
          "ref": "docs/shared-foundation-ownership.md"
        }
      ]
    },
    {
      "family_id": "templates",
      "index_ids": [
        "shared_asset_index"
      ],
      "opl_controls": [
        "shared template classes",
        "top-level template identity",
        "reusable cross-domain template index"
      ],
      "domain_controls": [
        "domain-specific instantiation",
        "workflow-local adaptation"
      ],
      "human_private_controls": [
        "draft templates before formal adoption"
      ],
      "must_not_move_into_opl_by_default": [
        "template execution ownership inside a domain"
      ],
      "governing_refs": [
        {
          "ref_kind": "repo_path",
          "ref": "docs/shared-foundation-ownership.md"
        }
      ]
    },
    {
      "family_id": "delivery_assets",
      "index_ids": [
        "shared_asset_index"
      ],
      "opl_controls": [
        "top-level discoverability",
        "cross-domain relation hints",
        "delivery-kind semantics"
      ],
      "domain_controls": [
        "formal deliverable truth",
        "exports",
        "submission or publish artifacts",
        "reviewable outputs"
      ],
      "human_private_controls": [
        "draft files before formal delivery admission"
      ],
      "must_not_move_into_opl_by_default": [
        "final delivery truth or release ownership"
      ],
      "governing_refs": [
        {
          "ref_kind": "repo_path",
          "ref": "docs/shared-foundation-ownership.md"
        }
      ]
    },
    {
      "family_id": "topic_memory",
      "index_ids": [
        "shared_memory_index"
      ],
      "opl_controls": [
        "reusable top-level topic identity",
        "cross-workstream topic index",
        "stable topic vocabulary"
      ],
      "domain_controls": [
        "domain-local evidence chains tied to studies, runs, or deliverables"
      ],
      "human_private_controls": [
        "exploratory notes",
        "early framing"
      ],
      "must_not_move_into_opl_by_default": [
        "domain-local evidence truth"
      ],
      "governing_refs": [
        {
          "ref_kind": "repo_path",
          "ref": "docs/shared-foundation-ownership.md"
        }
      ]
    },
    {
      "family_id": "review_memory",
      "index_ids": [
        "shared_memory_index"
      ],
      "opl_controls": [
        "cross-domain summary language when needed for discoverability"
      ],
      "domain_controls": [
        "full review history",
        "review state",
        "review decisions",
        "domain-specific review writeback"
      ],
      "human_private_controls": [
        "private reviewer notes",
        "temporary comments"
      ],
      "must_not_move_into_opl_by_default": [
        "canonical review truth"
      ],
      "governing_refs": [
        {
          "ref_kind": "repo_path",
          "ref": "docs/shared-foundation-ownership.md"
        }
      ]
    },
    {
      "family_id": "venue_memory",
      "index_ids": [
        "shared_memory_index"
      ],
      "opl_controls": [
        "top-level shared indexing",
        "reusable venue semantics"
      ],
      "domain_controls": [
        "domain-local venue fit decisions tied to concrete work products"
      ],
      "human_private_controls": [
        "personal preference notes not yet formalized"
      ],
      "must_not_move_into_opl_by_default": [
        "domain-specific submission truth"
      ],
      "governing_refs": [
        {
          "ref_kind": "repo_path",
          "ref": "docs/shared-foundation-ownership.md"
        }
      ]
    }
  ],
  "control_mode": {
    "mode": "reference_only_non_executing",
    "reference_only": true,
    "non_executing": true,
    "launch_execution": false,
    "route_actions": false,
    "mutate_domain_objects": false,
    "become_shared_truth_store": false
  },
  "boundary_guards": {
    "no_truth_shift": true,
    "no_mutation_ownership": true,
    "no_review_takeover": true,
    "no_publication_takeover": true,
    "no_domain_gateway_bypass": true,
    "forbidden_surface_roles": [
      "public_entry",
      "discovery_ready",
      "routed_action_ready",
      "execution_surface",
      "truth_owner",
      "approval_surface",
      "publish_control",
      "release_control"
    ]
  },
  "review_acceptance_coverage": {
    "required_surface_ids": [
      "opl_public_surface_index_doc",
      "opl_surface_lifecycle_map",
      "opl_surface_authority_matrix",
      "opl_surface_review_matrix"
    ],
    "acceptance_surface_id": "opl_gateway_acceptance_spec",
    "coverage_complete": false,
    "evidence_refs": [
      "docs/shared-foundation-ownership.md#readiness-before-public-admission",
      "contracts/opl-gateway/public-surface-index.json",
      "contracts/opl-gateway/surface-lifecycle-map.json",
      "contracts/opl-gateway/surface-authority-matrix.json",
      "contracts/opl-gateway/surface-review-matrix.json"
    ]
  },
  "public_admission_gate": {
    "overall_status": "blocked",
    "required_conditions": [
      {
        "condition_id": "object_scope_and_identifier_rules_frozen",
        "status": "ready",
        "evidence_refs": [
          "candidate_indexes[*].allowed_object_classes",
          "candidate_indexes[*].identifier_kinds"
        ]
      },
      {
        "condition_id": "owner_split_frozen",
        "status": "ready",
        "evidence_refs": [
          "owner_split[*]"
        ]
      },
      {
        "condition_id": "reference_only_control_mode_frozen",
        "status": "ready",
        "evidence_refs": [
          "control_mode"
        ]
      },
      {
        "condition_id": "no_takeover_guards_frozen",
        "status": "ready",
        "evidence_refs": [
          "boundary_guards"
        ]
      },
      {
        "condition_id": "review_acceptance_alignment_frozen",
        "status": "blocked",
        "evidence_refs": [
          "review_acceptance_coverage.coverage_complete=false"
        ]
      }
    ]
  }
}
